LICENSE
magicenv/__init__.py
magicenv/magicenv.py
magicenv-0.1.2.dist-info/LICENSE
magicenv-0.1.2.dist-info/WHEEL
magicenv-0.1.2.dist-info/METADATA
magicenv-0.1.2.dist-info/RECORD
