Metadata-Version: 2.1
Name: magicenv
Version: 0.1.2
Summary: Simple way to parse common datatypes from env vars.
Home-page: https://github.com/technocake/magicenv
License: MIT
Keywords: env,magic
Author: technocake
Author-email: robin.garen@gmail.com
Requires-Python: >=3.7,<4.0
Classifier: License :: OSI Approved :: MIT License
Classifier: Programming Language :: Python :: 3
Classifier: Programming Language :: Python :: 3.7
Classifier: Programming Language :: Python :: 3.8
Classifier: Programming Language :: Python :: 3.9
Project-URL: Repository, https://github.com/technocake/magicenv
